twn_generator/__init__.py
twn_generator/add_ops.py
twn_generator/bu_CSE.py
twn_generator/convert_tree_to_c.py
twn_generator/cse_common.py
twn_generator/dense_mat_mul_generator.py
twn_generator/helper_compute.py
twn_generator/sparse_mat_mul_generator.py
twn_generator/td_CSE.py
twn_generator-0.1.5.dist-info/LICENSE
twn_generator-0.1.5.dist-info/METADATA
twn_generator-0.1.5.dist-info/WHEEL
twn_generator-0.1.5.dist-info/top_level.txt
twn_generator-0.1.5.dist-info/RECORD
