Metadata-Version: 2.1
Name: twn-generator
Version: 0.1.5
Summary: A package to generate verilog for TNNs
Home-page: https://github.com/da-steve101/twn_generator
Author: Stephen Tridgell
Author-email: stephen.tridgell@sydney.edu.au
License: UNKNOWN
Platform: UNKNOWN
Classifier: Programming Language :: Python :: 3
Classifier: License :: OSI Approved :: GNU General Public License v3 (GPLv3)
Classifier: Operating System :: OS Independent
